odoo/addons/account_check_printing_caixabank/README.rst
odoo/addons/account_check_printing_caixabank/__init__.py
odoo/addons/account_check_printing_caixabank/__manifest__.py
odoo/addons/account_check_printing_caixabank/data/account_payment_check_report_data.xml
odoo/addons/account_check_printing_caixabank/data/report_paperformat.xml
odoo/addons/account_check_printing_caixabank/i18n/account_check_printing_caixabank.pot
odoo/addons/account_check_printing_caixabank/i18n/es.po
odoo/addons/account_check_printing_caixabank/report/__init__.py
odoo/addons/account_check_printing_caixabank/report/account_check_writing_report.xml
odoo/addons/account_check_printing_caixabank/report/check_print.py
odoo/addons/account_check_printing_caixabank/static/description/icon.png
odoo/addons/account_check_printing_caixabank/views/report_check_caixabank.xml
odoo11_addon_account_check_printing_caixabank-11.0.1.0.0.99.dev6.dist-info/METADATA
odoo11_addon_account_check_printing_caixabank-11.0.1.0.0.99.dev6.dist-info/RECORD
odoo11_addon_account_check_printing_caixabank-11.0.1.0.0.99.dev6.dist-info/WHEEL
odoo11_addon_account_check_printing_caixabank-11.0.1.0.0.99.dev6.dist-info/top_level.txt
